dynamic_metadata/__init__.py
dynamic_metadata/py.typed
dynamic_metadata/_compat/__init__.py
dynamic_metadata/_compat/typing.py
dynamic_metadata-0.1.0.dist-info/METADATA
dynamic_metadata-0.1.0.dist-info/WHEEL
dynamic_metadata-0.1.0.dist-info/licenses/LICENSE
dynamic_metadata-0.1.0.dist-info/RECORD
